<?xml version="1.0" encoding="windows-1252"?>
<Collection name="Spider" guid="{1EC821F6-CB2B-4371-8CD8-02F6DC44521B}" system="No" updateable="Yes" blockNavigatorNode="No" onInstallAddonGuid="{92AF3025-9BB9-4CF6-943E-8D0F678A31EB}"
  xmlns:xsi="http://www.w3.org/2001/XMLSchema-instance"
  xsi:noNamespaceSchemaLocation="https://contensive.s3.amazonaws.com/xsd/Collection.xsd"
>
	<HelpLink>http://support.contensive.com/spider-addon</HelpLink>
	<Help></Help>

	<Addon name="Social Media Install" guid="{92AF3025-9BB9-4CF6-943E-8D0F678A31EB}" type="Add-on">
		<Scripting language="VBScript" entryPoint="" timeout="5000">
			<Code><![CDATA[
		function f
			'
			' -- delete activex addon
			cp.db.executeNonQuery("delete from ccaggregatefunctions where ccguid='{E222CBF0-20B2-4221-93C3-03695F330C43}'")
		end function
		]]></Code>
		</Scripting>
	</Addon>
	<!--
		spider the nexct
	-->
	<Addon name="Spider" guid="{A5B29F03-4FEE-432F-8F34-704B7FB03560}" type="Add-on">
		<Copy></Copy>
		<CopyText></CopyText>
		<DotNetClass><![CDATA[Contensive.Addons.Spider.SpiderClass]]></DotNetClass>
		<ArgumentList></ArgumentList>
		<AsAjax>No</AsAjax>
		<Filter>No</Filter>
		<Help></Help>
		<HelpLink></HelpLink>
		<Icon link="" width="0" height="0" sprites="0" />
		<InIframe>No</InIframe>
		<BlockEditTools>No</BlockEditTools>
		<FormXML></FormXML>
		<IsInline>No</IsInline>
		<JavaScriptInHead></JavaScriptInHead>
		<MetaDescription></MetaDescription>
		<OtherHeadTags></OtherHeadTags>
		<Content>No</Content>
		<Template>No</Template>
		<Email>No</Email>
		<Admin>No</Admin>
		<OnPageEndEvent>No</OnPageEndEvent>
		<OnPageStartEvent>No</OnPageStartEvent>
		<OnBodyStart>No</OnBodyStart>
		<OnBodyEnd>No</OnBodyEnd>
		<RemoteMethod>No</RemoteMethod>
		<ProcessRunOnce>No</ProcessRunOnce>
		<ProcessInterval>1</ProcessInterval>
		<PageTitle></PageTitle>
		<RemoteAssetLink></RemoteAssetLink>
		<Styles></Styles>
		<Scripting language="" entryPoint="" timeout="5000"/>
	</Addon>
	<Addon name="Spider All Unspidered Links" guid="{073A0AB7-2CD1-4A8F-A3D8-B64581EB75E0}" type="Add-on">
		<Copy></Copy>
		<CopyText></CopyText>
		<DotNetClass><![CDATA[Contensive.Addons.Spider.SpiderAllUnspideredLinks]]></DotNetClass>
		<ArgumentList></ArgumentList>
		<AsAjax>No</AsAjax>
		<Filter>No</Filter>
		<Help></Help>
		<HelpLink></HelpLink>
		<Icon link="" width="0" height="0" sprites="0" />
		<InIframe>No</InIframe>
		<BlockEditTools>No</BlockEditTools>
		<FormXML></FormXML>
		<IsInline>No</IsInline>
		<JavaScriptInHead></JavaScriptInHead>
		<MetaDescription></MetaDescription>
		<OtherHeadTags></OtherHeadTags>
		<Content>No</Content>
		<Template>No</Template>
		<Email>No</Email>
		<Admin>No</Admin>
		<OnPageEndEvent>No</OnPageEndEvent>
		<OnPageStartEvent>No</OnPageStartEvent>
		<OnBodyStart>No</OnBodyStart>
		<OnBodyEnd>No</OnBodyEnd>
		<RemoteMethod>No</RemoteMethod>
		<ProcessRunOnce>No</ProcessRunOnce>
		<ProcessInterval></ProcessInterval>
		<PageTitle></PageTitle>
		<RemoteAssetLink></RemoteAssetLink>
		<Styles></Styles>
		<Scripting language="" entryPoint="" timeout="5000"/>
	</Addon>

	<Addon name="Spider Clean Up" guid="{68CF6E9D-C77C-4DE2-8552-FBDDE883573F}" type="Add-on">
		<Copy></Copy>
		<CopyText></CopyText>
		<DotNetClass><![CDATA[Contensive.Addons.Spider.SpiderCleanUp]]></DotNetClass>
		<ArgumentList></ArgumentList>
		<AsAjax>No</AsAjax>
		<Filter>No</Filter>
		<Help></Help>
		<HelpLink></HelpLink>
		<Icon link="" width="0" height="0" sprites="0" />
		<InIframe>No</InIframe>
		<BlockEditTools>No</BlockEditTools>
		<FormXML></FormXML>
		<IsInline>No</IsInline>
		<JavaScriptInHead></JavaScriptInHead>
		<MetaDescription></MetaDescription>
		<OtherHeadTags></OtherHeadTags>
		<Content>No</Content>
		<Template>No</Template>
		<Email>No</Email>
		<Admin>No</Admin>
		<OnPageEndEvent>No</OnPageEndEvent>
		<OnPageStartEvent>No</OnPageStartEvent>
		<OnBodyStart>No</OnBodyStart>
		<OnBodyEnd>No</OnBodyEnd>
		<RemoteMethod>No</RemoteMethod>
		<ProcessRunOnce>No</ProcessRunOnce>
		<ProcessInterval>3500</ProcessInterval>
		<PageTitle></PageTitle>
		<RemoteAssetLink></RemoteAssetLink>
		<Styles></Styles>
		<Scripting language="" entryPoint="" timeout="5000"/>
	</Addon>

	<CDef name="Spider Docs" active="1" adminOnly="0" allowAdd="1" allowCalendarEvents="0" allowContentChildTool="0" allowContentTracking="0" allowDelete="1" allowMetaContent="0" allowTopicRules="0" allowWorkflowAuthoring="0" authoringDataSourceName="Default" authoringTableName="ccSpiderDocs" contentDataSourceName="Default" contentTableName="ccSpiderDocs" defaultSortMethod="By Name" developerOnly="0" dropDownFieldList="Link" editorGroupName="" parent="" iconLink="" iconHeight="0" iconWidth="0" iconSprites="0" isBaseContent="0" guid="{8B30C8FC-FF19-45D3-B76E-B3557F85AE3D}" >
		<Field name="Name" active="True" adminOnly="False" authorable="True" caption="Name" developerOnly="False" editSortPriority="110" fieldType="Text" htmlContent="False" indexColumn="0" indexSortDirection="" indexSortOrder="0" indexWidth="30" redirectId="" redirectPath="" required="False" textBuffered="False" uniqueName="False" defaultValue="" rssTitle="False" rssDescription="False" memberSelectGroupId="0" editTab="" scramble="False" lookupList="" notEditable="False" password="False" readOnly="False" manyToManyRulePrimaryField="" manyToManyRuleSecondaryField="" isBaseField="False" lookupContent="" redirectContent="" manyToManyContent="" manyToManyRuleContent="" editorAddonId="" >
			<HelpDefault>The page title found when this link was fetched. If the page had no title or if there was a problem loading the page, the link is used.</HelpDefault>
		</Field>
		<Field name="Active" active="True" adminOnly="False" authorable="False" caption="Active" developerOnly="False" editSortPriority="200" fieldType="Boolean" htmlContent="False" indexColumn="99" indexSortDirection="" indexSortOrder="0" indexWidth="0" redirectId="" redirectPath="" required="False" textBuffered="False" uniqueName="False" defaultValue="1" rssTitle="False" rssDescription="False" memberSelectGroupId="0" editTab="" scramble="False" lookupList="" notEditable="False" password="False" readOnly="False" manyToManyRulePrimaryField="" manyToManyRuleSecondaryField="" isBaseField="False" lookupContent="" redirectContent="" manyToManyContent="" manyToManyRuleContent="" editorAddonId="" ></Field>
		<Field name="SortOrder" active="True" adminOnly="False" authorable="False" caption="Alpha Sort Order" developerOnly="False" editSortPriority="2000" fieldType="Text" htmlContent="False" indexColumn="99" indexSortDirection="" indexSortOrder="0" indexWidth="0" redirectId="" redirectPath="" required="False" textBuffered="False" uniqueName="False" defaultValue="" rssTitle="False" rssDescription="False" memberSelectGroupId="0" editTab="" scramble="False" lookupList="" notEditable="False" password="False" readOnly="False" manyToManyRulePrimaryField="" manyToManyRuleSecondaryField="" isBaseField="False" lookupContent="" redirectContent="" manyToManyContent="" manyToManyRuleContent="" editorAddonId="" ></Field>
		<Field name="Link" active="True" adminOnly="False" authorable="True" caption="Link" developerOnly="False" editSortPriority="1010" fieldType="Text" htmlContent="False" indexColumn="1" indexSortDirection="" indexSortOrder="1" indexWidth="40" redirectId="" redirectPath="" required="False" textBuffered="False" uniqueName="False" defaultValue="" rssTitle="False" rssDescription="False" memberSelectGroupId="0" editTab="" scramble="False" lookupList="" notEditable="False" password="False" readOnly="False" manyToManyRulePrimaryField="" manyToManyRuleSecondaryField="" isBaseField="False" lookupContent="" redirectContent="" manyToManyContent="" manyToManyRuleContent="" editorAddonId="" >
			<HelpDefault>The URL for this document, typically discovered on another page.</HelpDefault>
		</Field>
		<Field name="Host" active="True" adminOnly="False" authorable="True" caption="Host" developerOnly="False" editSortPriority="1020" fieldType="Text" htmlContent="False" indexColumn="99" indexSortDirection="" indexSortOrder="0" indexWidth="0" redirectId="" redirectPath="" required="False" textBuffered="False" uniqueName="False" defaultValue="" rssTitle="False" rssDescription="False" memberSelectGroupId="0" editTab="Internal" scramble="False" lookupList="" notEditable="False" password="False" readOnly="False" manyToManyRulePrimaryField="" manyToManyRuleSecondaryField="" isBaseField="False" lookupContent="" redirectContent="" manyToManyContent="" manyToManyRuleContent="" editorAddonId="" >
			<HelpDefault>The domain name portion of the link, calculated when the document is fetched.</HelpDefault>
		</Field>
		<Field name="Path" active="True" adminOnly="False" authorable="True" caption="Path" developerOnly="False" editSortPriority="1030" fieldType="Text" htmlContent="False" indexColumn="99" indexSortDirection="" indexSortOrder="0" indexWidth="0" redirectId="" redirectPath="" required="False" textBuffered="False" uniqueName="False" defaultValue="" rssTitle="False" rssDescription="False" memberSelectGroupId="0" editTab="Internal" scramble="False" lookupList="" notEditable="False" password="False" readOnly="False" manyToManyRulePrimaryField="" manyToManyRuleSecondaryField="" isBaseField="False" lookupContent="" redirectContent="" manyToManyContent="" manyToManyRuleContent="" editorAddonId="" >
			<HelpDefault>The path portion of the link, calculated when the document is fetched.</HelpDefault>
		</Field>
		<Field name="Page" active="True" adminOnly="False" authorable="True" caption="Page" developerOnly="False" editSortPriority="1040" fieldType="Text" htmlContent="False" indexColumn="99" indexSortDirection="" indexSortOrder="0" indexWidth="0" redirectId="" redirectPath="" required="False" textBuffered="False" uniqueName="False" defaultValue="" rssTitle="False" rssDescription="False" memberSelectGroupId="0" editTab="Internal" scramble="False" lookupList="" notEditable="False" password="False" readOnly="False" manyToManyRulePrimaryField="" manyToManyRuleSecondaryField="" isBaseField="False" lookupContent="" redirectContent="" manyToManyContent="" manyToManyRuleContent="" editorAddonId="" >
			<HelpDefault>The page name portion of the link, calculated when the document is fetched.</HelpDefault>
		</Field>
		<Field name="PageID" active="True" adminOnly="False" authorable="True" caption="Content Page" developerOnly="False" editSortPriority="1045" fieldType="Lookup" htmlContent="False" indexColumn="99" indexSortDirection="" indexSortOrder="0" indexWidth="0" redirectId="" redirectPath="" required="False" textBuffered="False" uniqueName="False" defaultValue="" rssTitle="False" rssDescription="False" memberSelectGroupId="0" editTab="Content" scramble="False" lookupList="" notEditable="False" password="False" readOnly="False" manyToManyRulePrimaryField="" manyToManyRuleSecondaryField="" isBaseField="False" lookupContent="Page Content" redirectContent="" manyToManyContent="" manyToManyRuleContent="" editorAddonId="" >
			<HelpDefault>The page content record id associated with this document.</HelpDefault>
		</Field>
		<Field name="UpToDate" active="True" adminOnly="False" authorable="True" caption="UpToDate" developerOnly="False" editSortPriority="1050" fieldType="Boolean" htmlContent="False" indexColumn="99" indexSortDirection="" indexSortOrder="0" indexWidth="0" redirectId="" redirectPath="" required="False" textBuffered="False" uniqueName="False" defaultValue="0" rssTitle="False" rssDescription="False" memberSelectGroupId="0" editTab="Status" scramble="False" lookupList="" notEditable="False" password="False" readOnly="False" manyToManyRulePrimaryField="" manyToManyRuleSecondaryField="" isBaseField="False" lookupContent="" redirectContent="" manyToManyContent="" manyToManyRuleContent="" editorAddonId="" >
			<HelpDefault>When true, this document has been successfully fetched and is current.</HelpDefault>
		</Field>
		<Field name="QueryString" active="True" adminOnly="False" authorable="True" caption="QueryString" developerOnly="False" editSortPriority="1055" fieldType="Text" htmlContent="False" indexColumn="99" indexSortDirection="" indexSortOrder="0" indexWidth="0" redirectId="" redirectPath="" required="False" textBuffered="False" uniqueName="False" defaultValue="" rssTitle="False" rssDescription="False" memberSelectGroupId="0" editTab="Internal" scramble="False" lookupList="" notEditable="False" password="False" readOnly="False" manyToManyRulePrimaryField="" manyToManyRuleSecondaryField="" isBaseField="False" lookupContent="" redirectContent="" manyToManyContent="" manyToManyRuleContent="" editorAddonId="" >
			<HelpDefault>The querystring portion of the link.</HelpDefault>
		</Field>
		<Field name="BodyText" active="True" adminOnly="False" authorable="True" caption="Body Text" developerOnly="False" editSortPriority="1115" fieldType="LongText" htmlContent="False" indexColumn="99" indexSortDirection="" indexSortOrder="0" indexWidth="0" redirectId="" redirectPath="" required="False" textBuffered="False" uniqueName="False" defaultValue="" rssTitle="False" rssDescription="False" memberSelectGroupId="0" editTab="Content" scramble="False" lookupList="" notEditable="False" password="False" readOnly="True" manyToManyRulePrimaryField="" manyToManyRuleSecondaryField="" isBaseField="False" lookupContent="" redirectContent="" manyToManyContent="" manyToManyRuleContent="" editorAddonId="" >
			<HelpDefault>The text content extracted from the document, used for full-text search.</HelpDefault>
		</Field>
		<Field name="PrimaryImageLink" active="True" adminOnly="False" authorable="True" caption="Primary Image Link" developerOnly="False" editSortPriority="1116" fieldType="Link" htmlContent="False" indexColumn="99" indexSortDirection="" indexSortOrder="0" indexWidth="0" redirectId="" redirectPath="" required="False" textBuffered="False" uniqueName="False" defaultValue="" rssTitle="False" rssDescription="False" memberSelectGroupId="0" editTab="Content" scramble="False" lookupList="" notEditable="False" password="False" readOnly="False" manyToManyRulePrimaryField="" manyToManyRuleSecondaryField="" isBaseField="False" lookupContent="" redirectContent="" manyToManyContent="" manyToManyRuleContent="" editorAddonId="" >
			<HelpDefault>The first image found within the page content, used in search results.</HelpDefault>
		</Field>
		<Field name="dateLastModified" active="True" adminOnly="False" authorable="True" caption="LastModified" developerOnly="False" editSortPriority="1120" fieldType="Date" htmlContent="False" indexColumn="99" indexSortDirection="" indexSortOrder="0" indexWidth="0" redirectId="" redirectPath="" required="False" textBuffered="False" uniqueName="False" defaultValue="" rssTitle="False" rssDescription="False" memberSelectGroupId="0" editTab="Meta" scramble="False" lookupList="" notEditable="False" password="False" readOnly="False" manyToManyRulePrimaryField="" manyToManyRuleSecondaryField="" isBaseField="False" lookupContent="" redirectContent="" manyToManyContent="" manyToManyRuleContent="" editorAddonId="" >
			<HelpDefault>The date the document content was last modified.</HelpDefault>
		</Field>
	</CDef>
	<Resource name="aospider.dll" type="executable" path="" />
</Collection>
